pconf/__init__.py
pconf/pconf.py
pconf/store/__init__.py
pconf/store/argv.py
pconf/store/env.py
pconf/store/file.py
pconf/store/memory.py
pconf-1.12.0.dist-info/licenses/LICENSE
pconf-1.12.0.dist-info/METADATA
pconf-1.12.0.dist-info/WHEEL
pconf-1.12.0.dist-info/top_level.txt
pconf-1.12.0.dist-info/RECORD
