Metadata-Version: 2.4
Name: pconf
Version: 1.12.0
Summary: Hierarchical python configuration with files, environment variables, command-line arguments.
Home-page: https://github.com/andrasmaroy/pconf
Author: Andras Maroy
Author-email: andras@maroy.hu
License: MIT
Keywords: configuration hierarchical
Classifier: Development Status :: 5 - Production/Stable
Classifier: Intended Audience :: Developers
Classifier: Topic :: Software Development :: Libraries :: Python Modules
Classifier: License :: OSI Approved :: MIT License
Classifier: Programming Language :: Python :: 3
Classifier: Programming Language :: Python :: 3.10
Classifier: Programming Language :: Python :: 3.11
Classifier: Programming Language :: Python :: 3.12
Classifier: Programming Language :: Python :: 3.13
Classifier: Programming Language :: Python :: 3.14
License-File: LICENSE
Requires-Dist: pyyaml
Requires-Dist: deepmerge
Provides-Extra: test
Requires-Dist: pytest; extra == "test"
Requires-Dist: mock; extra == "test"
Dynamic: author
Dynamic: author-email
Dynamic: classifier
Dynamic: description
Dynamic: home-page
Dynamic: keywords
Dynamic: license
Dynamic: license-file
Dynamic: provides-extra
Dynamic: requires-dist
Dynamic: summary
